nsvision/__init__.py
nsvision/_version.py
nsvision/classifier.py
nsvision/image_utils.py
nsvision/video_utils.py
nsvision/image_augmentation/__init__.py
nsvision/image_augmentation/cv2_augmentation.py
nsvision/s3bucket/__init__.py
nsvision/s3bucket/s3_utils.py
nsvision/tools/rename_files.py
nsvision/tools/split_data.py
nsvision/tools/split_data_gui.py
nsvision/tools/tumor_data_extractor.py
nsvision/xml/__init__.py
nsvision/xml/xml_conversion.py
nsvision/xml/xml_pipeline.py
nsvision-0.1.9.dist-info/LICENSE
nsvision-0.1.9.dist-info/METADATA
nsvision-0.1.9.dist-info/WHEEL
nsvision-0.1.9.dist-info/entry_points.txt
nsvision-0.1.9.dist-info/top_level.txt
nsvision-0.1.9.dist-info/RECORD
