Metadata-Version: 2.1
Name: nsvision
Version: 0.1.9
Summary: nsvision - Computer Vision Wrapper built on top of PIL, cv2 and Numpy
Home-page: https://github.com/Nsemble/nsvision
Author: Nsemble.ai
Author-email: admin@nsemble.ai
License: MIT
Platform: UNKNOWN
Classifier: Topic :: Scientific/Engineering :: Artificial Intelligence
Classifier: Programming Language :: Python :: 3.6
Classifier: Programming Language :: Python :: 3.7
Classifier: License :: OSI Approved :: MIT License
Classifier: Topic :: Utilities
Requires-Python: >=3.6
Requires-Dist: numpy (==1.18.3)
Requires-Dist: Pillow (==7.0.0)
